ga4gh/__init__.py
ga4gh/testbed/__init__.py
ga4gh/testbed/mixins/__init__.py
ga4gh/testbed/mixins/has_message.py
ga4gh/testbed/mixins/has_status.py
ga4gh/testbed/mixins/has_summary.py
ga4gh/testbed/mixins/has_timestamps.py
ga4gh/testbed/report/__init__.py
ga4gh/testbed/report/case.py
ga4gh/testbed/report/constants.py
ga4gh/testbed/report/phase.py
ga4gh/testbed/report/report.py
ga4gh/testbed/report/status.py
ga4gh/testbed/report/summary.py
ga4gh/testbed/report/test.py
ga4gh/testbed/submit/__init__.py
ga4gh/testbed/submit/report_submitter.py
tests/__init__.py
tests/test_e2e/__init__.py
tests/test_e2e/test_report_finalization_serialization.py
tests/test_unit/__init__.py
tests/test_unit/test_ga4gh/__init__.py
tests/test_unit/test_ga4gh/test_testbed/__init__.py
tests/test_unit/test_ga4gh/test_testbed/test_report/__init__.py
tests/test_unit/test_ga4gh/test_testbed/test_report/test_case.py
tests/test_unit/test_ga4gh/test_testbed/test_report/test_phase.py
tests/test_unit/test_ga4gh/test_testbed/test_report/test_report.py
tests/test_unit/test_ga4gh/test_testbed/test_report/test_summary.py
tests/test_unit/test_ga4gh/test_testbed/test_report/test_test.py
ga4gh_testbed_lib-0.2.2.dist-info/LICENSE
ga4gh_testbed_lib-0.2.2.dist-info/METADATA
ga4gh_testbed_lib-0.2.2.dist-info/WHEEL
ga4gh_testbed_lib-0.2.2.dist-info/top_level.txt
ga4gh_testbed_lib-0.2.2.dist-info/RECORD
