Metadata-Version: 2.1
Name: ga4gh-testbed-lib
Version: 0.2.2
Summary: Python library for creating GA4GH testbed reports according to a harmonized, cross-workstream schema
Home-page: https://github.com/ga4gh/ga4gh-testbed-lib
Author: Jeremy Adams
Author-email: jeremy.adams@ga4gh.org
Classifier: Programming Language :: Python :: 3.6
Classifier: Programming Language :: Python :: 3.7
Classifier: License :: OSI Approved :: Apache Software License
Classifier: Operating System :: OS Independent
Classifier: Natural Language :: English
Classifier: Topic :: Scientific/Engineering :: Bio-Informatics
License-File: LICENSE
